brute_force_training/__init__.py
brute_force_training/cli.py
brute_force_training/config.py
brute_force_training/datasets/__init__.py
brute_force_training/datasets/text_only.py
brute_force_training/datasets/vision_language.py
brute_force_training/trainers/__init__.py
brute_force_training/trainers/base.py
brute_force_training/trainers/lfm2_vl.py
brute_force_training/trainers/qwen25_vl.py
brute_force_training/trainers/qwen2_vl.py
brute_force_training/trainers/qwen3.py
brute_force_training/utils/__init__.py
brute_force_training/utils/documentation.py
brute_force_training/utils/evaluation.py
brute_force_training/utils/image_utils.py
brute_force_training/utils/tokenization.py
brute_force_training-0.0.2.dist-info/licenses/LICENSE
brute_force_training-0.0.2.dist-info/METADATA
brute_force_training-0.0.2.dist-info/WHEEL
brute_force_training-0.0.2.dist-info/entry_points.txt
brute_force_training-0.0.2.dist-info/top_level.txt
brute_force_training-0.0.2.dist-info/RECORD
