Metadata-Version: 2.4
Name: brute-force-training
Version: 0.0.2
Summary: A no-thrills Python package for finetuning Vision-Language Models (VLMs)
Author: William J.B. Mattingly
License: MIT License
Project-URL: Homepage, https://github.com/wjbmattingly/brute-force-training
Project-URL: Repository, https://github.com/wjbmattingly/brute-force-training
Project-URL: Issues, https://github.com/wjbmattingly/brute-force-training/issues
Classifier: Development Status :: 3 - Alpha
Classifier: Intended Audience :: Developers
Classifier: Intended Audience :: Science/Research
Classifier: License :: OSI Approved :: MIT License
Classifier: Operating System :: OS Independent
Classifier: Programming Language :: Python :: 3
Classifier: Programming Language :: Python :: 3.8
Classifier: Programming Language :: Python :: 3.9
Classifier: Programming Language :: Python :: 3.10
Classifier: Programming Language :: Python :: 3.11
Classifier: Topic :: Scientific/Engineering :: Artificial Intelligence
Classifier: Topic :: Software Development :: Libraries :: Python Modules
Requires-Python: >=3.8
License-File: LICENSE
Requires-Dist: torch
Requires-Dist: transformers
Requires-Dist: datasets
Requires-Dist: Pillow
Requires-Dist: tqdm
Requires-Dist: qwen-vl-utils
Requires-Dist: matplotlib
Requires-Dist: seaborn
Requires-Dist: python-Levenshtein
Provides-Extra: dev
Requires-Dist: pytest>=6.0; extra == "dev"
Requires-Dist: black>=22.0; extra == "dev"
Requires-Dist: flake8>=4.0; extra == "dev"
Requires-Dist: isort>=5.0; extra == "dev"
Dynamic: license-file
Dynamic: requires-python
